import_export-stubs/METADATA.toml
import_export-stubs/__init__.pyi
import_export-stubs/admin.pyi
import_export-stubs/command_utils.pyi
import_export-stubs/declarative.pyi
import_export-stubs/exceptions.pyi
import_export-stubs/fields.pyi
import_export-stubs/forms.pyi
import_export-stubs/instance_loaders.pyi
import_export-stubs/mixins.pyi
import_export-stubs/options.pyi
import_export-stubs/py.typed
import_export-stubs/resources.pyi
import_export-stubs/results.pyi
import_export-stubs/signals.pyi
import_export-stubs/tmp_storages.pyi
import_export-stubs/utils.pyi
import_export-stubs/widgets.pyi
import_export-stubs/formats/__init__.pyi
import_export-stubs/formats/base_formats.pyi
import_export-stubs/templatetags/__init__.pyi
import_export-stubs/templatetags/import_export_tags.pyi
management-stubs/METADATA.toml
management-stubs/__init__.pyi
management-stubs/py.typed
management-stubs/commands/__init__.pyi
management-stubs/commands/export.pyi
management-stubs/commands/import.pyi
types_django_import_export-4.4.0.20260113.dist-info/licenses/LICENSE
types_django_import_export-4.4.0.20260113.dist-info/METADATA
types_django_import_export-4.4.0.20260113.dist-info/WHEEL
types_django_import_export-4.4.0.20260113.dist-info/top_level.txt
types_django_import_export-4.4.0.20260113.dist-info/RECORD
